{
  "seheri": {
    "title": {
      "en": "Roza Niyyat",
      "bn": "রোজার নিয়ত"
    },
    "arabic": "نَوَيْتُ اَنْ اُصُوْمَ غَدًا مِّنْ شَهْرِ رَمْضَانَ الْمُبَارَكِ فَرْضًا لَكَ يَا اللهُ فَتَقَبَّلْ مِنِّى اِنَّكَ اَنْتَ السَّمِيْعُ الْعَلِيْمُ",
    "transliteration": {
      "en": "Nawaitu an asuma ghadam min shahri ramadanal mubarak, fardal laka ya Allahu fataqabbal minni innaka antas sami'ul alim.",
      "bn": "নাওয়াইতু আন আসুমা গাদাম, মিন শাহরি রামাদানাল মুবারাক; ফারদাল লাকা ইয়া আল্লাহু, ফাতাকাব্বাল মিন্নি ইন্নাকা আন্তাস সামিউল আলিম।"
    },
    "translation": {
      "en": "O Allah! I intend to keep tomorrow's obligatory fast of the blessed month of Ramadan for Your sake. So accept it from me. Surely You are the All-Hearing, All-Knowing.",
      "bn": "হে আল্লাহ! আমি আগামীকাল পবিত্র রমজানের তোমার পক্ষ থেকে নির্ধারিত ফরজ রোজা রাখার নিয়ত করলাম। অতএব তুমি আমার পক্ষ থেকে তা কবুল কর। নিশ্চয়ই তুমি সর্বশ্রোতা, সর্বজ্ঞ।"
    }
  },
  "iftar": {
    "title": {
      "en": "Iftar Dua",
      "bn": "ইফতারের দোয়া"
    },
    "arabic": "اللهم إني لك صمت وعلى رزقك أفطرت",
    "transliteration": {
      "en": "Allahumma inni laka sumtu wa ‘ala rizqika aftartu",
      "bn": "আল্লাহুম্মা ইন্নি লাকা সুমতু ওয়া ‘আলা রিজকিকা আফতারতু"
    },
    "translation": {
      "en": "O Allah! I fasted for You, and I break my fast with Your sustenance.",
      "bn": "হে আল্লাহ! আমি আপনার জন্য রোজা রেখেছি এবং আপনার রিজিক দিয়ে ইফতার করছি।"
    }
  }
}
